xasm/.gitignore
xasm/__init__.py
xasm/assemble.py
xasm/pyc_convert.py
xasm/version.py
xasm/write_pyc.py
xasm/xasm_cli.py
xasm-1.2.2.dist-info/licenses/LICENSE.gpl2
xasm-1.2.2.dist-info/METADATA
xasm-1.2.2.dist-info/WHEEL
xasm-1.2.2.dist-info/entry_points.txt
xasm-1.2.2.dist-info/top_level.txt
xasm-1.2.2.dist-info/RECORD
